watchman_agent/__init__.py
watchman_agent/__main__.py
watchman_agent/runner.py
watchman_agent/test.py
watchman_agent_v2/__init__.py
watchman_agent_v2/agent.py
watchman_agent_v2/configs/__init__.py
watchman_agent_v2/core/__init__.py
watchman_agent_v2/core/ad/Ad_assets.py
watchman_agent_v2/core/ad/Ad_users.py
watchman_agent_v2/core/ad/__init__.py
watchman_agent_v2/core/ad/configure.py
watchman_agent_v2/core/ad/get_apps.py
watchman_agent_v2/core/ad/ldap_client.py
watchman_agent_v2/core/ad/ldap_client_2.py
watchman_agent_v2/core/agents/__init__.py
watchman_agent_v2/core/agents/base_agent.py
watchman_agent_v2/core/agents/local_agent.py
watchman_agent_v2/core/agents/network_agent.py
watchman_agent_v2/core/auth/__init__.py
watchman_agent_v2/core/auth/credential_vault.py
watchman_agent_v2/core/auth/crypto_manager.py
watchman_agent_v2/core/commands/__init__.py
watchman_agent_v2/core/commands/active_directory.py
watchman_agent_v2/core/commands/configure.py
watchman_agent_v2/core/commands/cron.py
watchman_agent_v2/core/commands/cron_old.py
watchman_agent_v2/core/commands/generate_key.py
watchman_agent_v2/core/commands/run.py
watchman_agent_v2/core/commands/server.py
watchman_agent_v2/core/config/__init__.py
watchman_agent_v2/core/config/config_manager.py
watchman_agent_v2/core/config/settings/__init__.py
watchman_agent_v2/core/config/settings/api_config.py
watchman_agent_v2/core/config/settings/cron_config.py
watchman_agent_v2/core/config/settings/export_config.py
watchman_agent_v2/core/config/settings/log_config.py
watchman_agent_v2/core/config/settings/mode_config.py
watchman_agent_v2/core/config/settings/network_config.py
watchman_agent_v2/core/config/settings/protocols_config.py
watchman_agent_v2/core/protocols/__init__.py
watchman_agent_v2/core/protocols/http.py
watchman_agent_v2/core/protocols/ldap.py
watchman_agent_v2/core/protocols/ldaps.py
watchman_agent_v2/core/protocols/protocol_factory.py
watchman_agent_v2/core/protocols/snmp.py
watchman_agent-3.0.5.3.dist-info/METADATA
watchman_agent-3.0.5.3.dist-info/WHEEL
watchman_agent-3.0.5.3.dist-info/entry_points.txt
watchman_agent-3.0.5.3.dist-info/top_level.txt
watchman_agent-3.0.5.3.dist-info/RECORD
